README.txt
setup.py
bibolamazi_gui/__init__.py
bibolamazi_gui/bibconfigsynthigh.py
bibolamazi_gui/bibolamazi_gui.py
bibolamazi_gui/favorites.py
bibolamazi_gui/filterinstanceeditor.py
bibolamazi_gui/helpbrowser.py
bibolamazi_gui/openbibfile.py
bibolamazi_gui/overlistbuttonwidget.py
bibolamazi_gui/settingswidget.py
bibolamazi_gui/sourcelisteditor.py
bibolamazi_gui/version.py
bibolamazi_gui.egg-info/PKG-INFO
bibolamazi_gui.egg-info/SOURCES.txt
bibolamazi_gui.egg-info/dependency_links.txt
bibolamazi_gui.egg-info/requires.txt
bibolamazi_gui.egg-info/top_level.txt
bibolamazi_gui.egg-info/zip-safe
bibolamazi_gui/qtauto/__init__.py
bibolamazi_gui/qtauto/bibolamazi_res_rc.py
bibolamazi_gui/qtauto/ui_favoritesoverbtns.py
bibolamazi_gui/qtauto/ui_filterinstanceeditor.py
bibolamazi_gui/qtauto/ui_helpbrowser.py
bibolamazi_gui/qtauto/ui_mainwidget.py
bibolamazi_gui/qtauto/ui_openbibfile.py
bibolamazi_gui/qtauto/ui_overlistbuttonwidget.py
bibolamazi_gui/qtauto/ui_settingswidget.py
bibolamazi_gui/qtauto/ui_sourcelisteditor.py
bin/bibolamazi_gui